_allium_hash.cpython-39-darwin.so
allium.cpython-39-darwin.so
allium_hash.cpython-39-darwin.so
allium_hash-1.0.5.dist-info/METADATA
allium_hash-1.0.5.dist-info/WHEEL
allium_hash-1.0.5.dist-info/top_level.txt
allium_hash-1.0.5.dist-info/RECORD
