Metadata-Version: 2.1
Name: allium-hash
Version: 1.0.5
Summary: Bindings for Allium proof of work used by Garlicoin
Home-page: https://github.com/ryan-shaw/allium-hash-python
Author: Ryan Shaw
Author-email: ryan@rshaw.me
License: UNKNOWN
Platform: UNKNOWN
